__init__.py
PyOData1C/__init__.py
PyOData1C/exeptions.py
PyOData1C/http.py
PyOData1C/models.py
PyOData1C/odata.py
PyOData1C/sample.py
PyOData1C-0.0.9.dist-info/LICENSE
PyOData1C-0.0.9.dist-info/METADATA
PyOData1C-0.0.9.dist-info/WHEEL
PyOData1C-0.0.9.dist-info/top_level.txt
PyOData1C-0.0.9.dist-info/RECORD
