Metadata-Version: 2.1
Name: PyOData1C
Version: 0.0.9
Summary: ORM for 1C
Author-email: Aleksey Kravtsun <kravtsun.aleksey@gmail.com>
Project-URL: Homepage, https://github.com/kr-aleksey/PyOData1C
Project-URL: AuthorGitHub, https://github.com/kr-aleksey
Classifier: Programming Language :: Python :: 3
Classifier: License :: OSI Approved :: MIT License
Classifier: Operating System :: MacOS
Classifier: Operating System :: Microsoft :: Windows
Classifier: Operating System :: POSIX :: Linux
Classifier: Development Status :: 4 - Beta
Requires-Python: >=3.11
License-File: LICENSE
Requires-Dist: pydantic>=2.9
Requires-Dist: requests>=2.32
